requirements.txt
setup.py
django_configurations_templates/__init__.py
django_configurations_templates.egg-info/PKG-INFO
django_configurations_templates.egg-info/SOURCES.txt
django_configurations_templates.egg-info/dependency_links.txt
django_configurations_templates.egg-info/requires.txt
django_configurations_templates.egg-info/top_level.txt