Metadata-Version: 2.1
Name: django-configurations-templates
Version: 2020.7.1
Summary: django-configurations templates settings
Home-page: https://github.com/andrewp-as-is/django-configurations-templates.py
License: Unlicense
Keywords: django templates configuration
Platform: UNKNOWN
Classifier: Framework :: Django
Classifier: License :: Public Domain
Classifier: Operating System :: OS Independent
Classifier: Programming Language :: Python :: 3
